alfrodull/__init__.py
alfrodull/main.py
alfrodull/util.py
alfrodull/animation/__init__.py
alfrodull/animation/fade.py
alfrodull/animation/inside_out.py
alfrodull/animation/outside_in.py
alfrodull/devices/__init__.py
alfrodull/devices/blinkstick.py
alfrodull/events/__init__.py
alfrodull/events/init.py
alfrodull/events/shutdown.py
alfrodull/events/sleep.py
alfrodull/events/wakeup.py
tests/__init__.py
tests/animation/__init__.py
tests/animation/conftest.py
tests/animation/test_fade.py
tests/animation/test_inside_out.py
tests/animation/test_outside_in.py
alfrodull-0.1.0.dist-info/LICENSE
alfrodull-0.1.0.dist-info/METADATA
alfrodull-0.1.0.dist-info/WHEEL
alfrodull-0.1.0.dist-info/entry_points.txt
alfrodull-0.1.0.dist-info/top_level.txt
alfrodull-0.1.0.dist-info/RECORD
