Metadata-Version: 2.1
Name: alfrodull
Version: 0.1.0
Summary: Alfrodull is a utility that controls lights based on the a computers events
Home-page: https://github.com/phillebaba/alfrodull
Author: Philip Laine
Author-email: philip.laine@gmail.com
License: UNKNOWN
Platform: UNKNOWN
Classifier: Programming Language :: Python :: 3
Classifier: License :: OSI Approved :: MIT License
Classifier: Operating System :: POSIX :: Linux
Requires-Dist: atomicwrites (==1.3.0)
Requires-Dist: attrs (==19.1.0)
Requires-Dist: BlinkStick (==1.1.8)
Requires-Dist: dbus-python (==1.2.8)
Requires-Dist: importlib-metadata (==0.17)
Requires-Dist: more-itertools (==7.0.0)
Requires-Dist: packaging (==19.0)
Requires-Dist: pluggy (==0.12.0)
Requires-Dist: py (==1.8.0)
Requires-Dist: pyaml (==19.4.1)
Requires-Dist: pycairo (==1.18.1)
Requires-Dist: pydbus (==0.6.0)
Requires-Dist: PyGObject (==3.32.1)
Requires-Dist: pyparsing (==2.4.0)
Requires-Dist: pytest (==4.6.2)
Requires-Dist: pyusb (==1.0.0b1)
Requires-Dist: PyYAML (==5.1)
Requires-Dist: six (==1.12.0)
Requires-Dist: wcwidth (==0.1.7)
Requires-Dist: zipp (==0.5.1)
